LICENSE
MANIFEST.in
NOTICE
README.md
requirements.txt
setup.cfg
setup.py
compiler/__init__.py
compiler/api/__init__.py
compiler/api/compiler.py
compiler/api/source/auth_key.tl
compiler/api/source/main_api.tl
compiler/api/source/sys_msgs.tl
compiler/api/template/combinator.txt
compiler/api/template/type.txt
compiler/errors/__init__.py
compiler/errors/compiler.py
compiler/errors/sort.py
compiler/errors/source/303_SEE_OTHER.tsv
compiler/errors/source/400_BAD_REQUEST.tsv
compiler/errors/source/401_UNAUTHORIZED.tsv
compiler/errors/source/403_FORBIDDEN.tsv
compiler/errors/source/406_NOT_ACCEPTABLE.tsv
compiler/errors/source/420_FLOOD.tsv
compiler/errors/source/500_INTERNAL_SERVER_ERROR.tsv
compiler/errors/source/503_SERVICE_UNAVAILABLE.tsv
compiler/errors/template/class.txt
compiler/errors/template/sub_class.txt
tests/__init__.py
tests/test_file_id.py
tests/filters/__init__.py
tests/filters/test_command.py
ubotlibs/__init__.py
ubotlibs/assistant.py
ubotlibs/client.py
ubotlibs/dispatcher.py
ubotlibs/emoji.py
ubotlibs/file_id.py
ubotlibs/filters.py
ubotlibs/mime_types.py
ubotlibs/py.typed
ubotlibs/sync.py
ubotlibs/utils.py
ubotlibs.egg-info/PKG-INFO
ubotlibs.egg-info/SOURCES.txt
ubotlibs.egg-info/dependency_links.txt
ubotlibs.egg-info/not-zip-safe
ubotlibs.egg-info/requires.txt
ubotlibs.egg-info/top_level.txt
ubotlibs/connection/__init__.py
ubotlibs/connection/connection.py
ubotlibs/connection/transport/__init__.py
ubotlibs/connection/transport/tcp/__init__.py
ubotlibs/connection/transport/tcp/tcp.py
ubotlibs/connection/transport/tcp/tcp_abridged.py
ubotlibs/connection/transport/tcp/tcp_abridged_o.py
ubotlibs/connection/transport/tcp/tcp_full.py
ubotlibs/connection/transport/tcp/tcp_intermediate.py
ubotlibs/connection/transport/tcp/tcp_intermediate_o.py
ubotlibs/crypto/__init__.py
ubotlibs/crypto/aes.py
ubotlibs/crypto/mtproto.py
ubotlibs/crypto/prime.py
ubotlibs/crypto/rsa.py
ubotlibs/enums/__init__.py
ubotlibs/enums/auto_name.py
ubotlibs/enums/chat_action.py
ubotlibs/enums/chat_event_action.py
ubotlibs/enums/chat_member_status.py
ubotlibs/enums/chat_members_filter.py
ubotlibs/enums/chat_type.py
ubotlibs/enums/message_entity_type.py
