Metadata-Version: 2.1
Name: ubotlibs
Version: 0.0.9
Summary: ubotlibs - Telegram MTProto API Client Library for Python.
Home-page: https://github.com/hitokizzy/ubotlibs
Author: Hamba
Author-email: tuyultermux777@gmail.com
License: GNU Lesser General Public License v3.0 (LGPL-3.0)
Project-URL: Bug Tracker, https://github.com/iskandar777-dar/ubotlibs/issues
Project-URL: Documentation, https://ubotlibs.tech
Project-URL: Source Code, https://github.com/iskandar777-dar/ubotlibs
Classifier: Programming Language :: Python :: 3
Classifier: Programming Language :: Python :: 3.8
Classifier: Programming Language :: Python :: 3.9
Classifier: Programming Language :: Python :: 3.10
Classifier: License :: OSI Approved :: GNU General Public License v3 (GPLv3)
Classifier: Operating System :: OS Independent
Requires-Python: ~=3.7
License-File: LICENSE
License-File: NOTICE
